credeed_pdf_to_markdown/__init__.py
credeed_pdf_to_markdown/converter.py
credeed_pdf_to_markdown/utils.py
credeed_pdf_to_markdown-0.1.0.dist-info/METADATA
credeed_pdf_to_markdown-0.1.0.dist-info/WHEEL
credeed_pdf_to_markdown-0.1.0.dist-info/entry_points.txt
credeed_pdf_to_markdown-0.1.0.dist-info/top_level.txt
credeed_pdf_to_markdown-0.1.0.dist-info/RECORD
