Metadata-Version: 2.4
Name: credeed-pdf-to-markdown
Version: 0.1.0
Summary: Convert PDF to Markdown using Azure AI Document Intelligence and upload to S3. Provided by the Credeed AI team, it can be used for AI Agent to understand PDF documents.
Home-page: https://github.com/credeed/credeed-pdf-to-markdown
Author: Credeed AI
Author-email: dev@credeed.com
License: MIT License
Keywords: pdf,markdown,azure,s3,document-intelligence,conversion
Requires-Python: >=3.7
Requires-Dist: boto3
Requires-Dist: azure-ai-documentintelligence>=1.0.0
